{
  "7993": {
    "transaction_id": 7993,
    "product": "CF03-007",
    "is_important": true,
    "lcd_date": "2024-01-21T00:00:00",
    "total_sequences": 4,
    "tasks": [
      {
        "sequence": 1,
        "processing_time": 1.9,
        "capable_machines": [
          0,
          1,
          2
        ],
        "status": "pending"
      },
      {
        "sequence": 2,
        "processing_time": 1.5,
        "capable_machines": [
          0,
          1,
          2,
          3,
          4,
          5,
          6,
          7
        ],
        "status": "pending"
      },
      {
        "sequence": 3,
        "processing_time": 1.4,
        "capable_machines": [
          0,
          1,
          2,
          3,
          4,
          5,
          6,
          7
        ],
        "status": "pending"
      },
      {
        "sequence": 4,
        "processing_time": 1.3,
        "capable_machines": [
          2,
          3,
          4,
          5,
          6,
          7,
          8,
          9
        ],
        "status": "pending"
      }
    ]
  },
  "7882": {
    "transaction_id": 7882,
    "product": "CP08-428A",
    "is_important": false,
    "lcd_date": "2024-02-24T00:00:00",
    "total_sequences": 3,
    "tasks": [
      {
        "sequence": 1,
        "processing_time": 2.5,
        "capable_machines": [
          0,
          1,
          2
        ],
        "status": "pending"
      },
      {
        "sequence": 2,
        "processing_time": 1.9,
        "capable_machines": [
          0,
          1,
          2,
          3,
          4,
          5,
          6,
          7
        ],
        "status": "pending"
      },
      {
        "sequence": 3,
        "processing_time": 1.8,
        "capable_machines": [
          0,
          1,
          2,
          3,
          4,
          5,
          6,
          7
        ],
        "status": "pending"
      }
    ]
  },
  "7881": {
    "transaction_id": 7881,
    "product": "CP08-428",
    "is_important": false,
    "lcd_date": "2024-02-27T00:00:00",
    "total_sequences": 9,
    "tasks": [
      {
        "sequence": 12,
        "processing_time": 1.3,
        "capable_machines": [
          2,
          3,
          4,
          5,
          6,
          7,
          8,
          9
        ],
        "status": "pending"
      },
      {
        "sequence": 13,
        "processing_time": 1.0,
        "capable_machines": [
          2,
          3,
          4,
          5,
          6,
          7,
          8,
          9
        ],
        "status": "pending"
      },
      {
        "sequence": 14,
        "processing_time": 1.1,
        "capable_machines": [
          2,
          3,
          4,
          5,
          6,
          7,
          8,
          9
        ],
        "status": "pending"
      },
      {
        "sequence": 15,
        "processing_time": 1.1,
        "capable_machines": [
          2,
          3,
          4,
          5,
          6,
          7,
          8,
          9
        ],
        "status": "pending"
      },
      {
        "sequence": 16,
        "processing_time": 1.3,
        "capable_machines": [
          2,
          3,
          4,
          5,
          6,
          7,
          8,
          9
        ],
        "status": "pending"
      },
      {
        "sequence": 17,
        "processing_time": 1.3,
        "capable_machines": [
          2,
          3,
          4,
          5,
          6,
          7,
          8,
          9
        ],
        "status": "pending"
      },
      {
        "sequence": 18,
        "processing_time": 1.4,
        "capable_machines": [
          2,
          3,
          4,
          5,
          6,
          7,
          8,
          9
        ],
        "status": "pending"
      },
      {
        "sequence": 19,
        "processing_time": 1.0,
        "capable_machines": [
          2,
          3,
          4,
          5,
          6,
          7,
          8,
          9
        ],
        "status": "pending"
      },
      {
        "sequence": 20,
        "processing_time": 1.2,
        "capable_machines": [
          2,
          3,
          4,
          5,
          6,
          7,
          8,
          9
        ],
        "status": "pending"
      }
    ]
  },
  "7880": {
    "transaction_id": 7880,
    "product": "CP08-428",
    "is_important": false,
    "lcd_date": "2024-03-08T00:00:00",
    "total_sequences": 9,
    "tasks": [
      {
        "sequence": 12,
        "processing_time": 1.3,
        "capable_machines": [
          2,
          3,
          4,
          5,
          6,
          7,
          8,
          9
        ],
        "status": "pending"
      },
      {
        "sequence": 13,
        "processing_time": 1.0,
        "capable_machines": [
          2,
          3,
          4,
          5,
          6,
          7,
          8,
          9
        ],
        "status": "pending"
      },
      {
        "sequence": 14,
        "processing_time": 1.1,
        "capable_machines": [
          2,
          3,
          4,
          5,
          6,
          7,
          8,
          9
        ],
        "status": "pending"
      },
      {
        "sequence": 15,
        "processing_time": 1.1,
        "capable_machines": [
          2,
          3,
          4,
          5,
          6,
          7,
          8,
          9
        ],
        "status": "pending"
      },
      {
        "sequence": 16,
        "processing_time": 1.3,
        "capable_machines": [
          2,
          3,
          4,
          5,
          6,
          7,
          8,
          9
        ],
        "status": "pending"
      },
      {
        "sequence": 17,
        "processing_time": 1.3,
        "capable_machines": [
          2,
          3,
          4,
          5,
          6,
          7,
          8,
          9
        ],
        "status": "pending"
      },
      {
        "sequence": 18,
        "processing_time": 1.4,
        "capable_machines": [
          2,
          3,
          4,
          5,
          6,
          7,
          8,
          9
        ],
        "status": "pending"
      },
      {
        "sequence": 19,
        "processing_time": 1.0,
        "capable_machines": [
          2,
          3,
          4,
          5,
          6,
          7,
          8,
          9
        ],
        "status": "pending"
      },
      {
        "sequence": 20,
        "processing_time": 1.2,
        "capable_machines": [
          2,
          3,
          4,
          5,
          6,
          7,
          8,
          9
        ],
        "status": "pending"
      }
    ]
  },
  "7879": {
    "transaction_id": 7879,
    "product": "CP08-427",
    "is_important": false,
    "lcd_date": "2024-03-01T00:00:00",
    "total_sequences": 3,
    "tasks": [
      {
        "sequence": 1,
        "processing_time": 1.9,
        "capable_machines": [
          0,
          1,
          2
        ],
        "status": "pending"
      },
      {
        "sequence": 2,
        "processing_time": 1.5,
        "capable_machines": [
          0,
          1,
          2,
          3,
          4,
          5,
          6,
          7
        ],
        "status": "pending"
      },
      {
        "sequence": 3,
        "processing_time": 1.4,
        "capable_machines": [
          0,
          1,
          2,
          3,
          4,
          5,
          6,
          7
        ],
        "status": "pending"
      }
    ]
  },
  "7878": {
    "transaction_id": 7878,
    "product": "CP08-426",
    "is_important": false,
    "lcd_date": "2024-02-07T00:00:00",
    "total_sequences": 2,
    "tasks": [
      {
        "sequence": 1,
        "processing_time": 1.9,
        "capable_machines": [
          6,
          7,
          8
        ],
        "status": "pending"
      },
      {
        "sequence": 2,
        "processing_time": 1.5,
        "capable_machines": [
          0,
          1,
          2,
          3,
          4,
          5,
          6,
          7
        ],
        "status": "pending"
      }
    ]
  },
  "7877": {
    "transaction_id": 7877,
    "product": "CP08-425",
    "is_important": false,
    "lcd_date": "2024-03-09T00:00:00",
    "total_sequences": 3,
    "tasks": [
      {
        "sequence": 1,
        "processing_time": 1.9,
        "capable_machines": [
          3,
          4,
          5
        ],
        "status": "pending"
      },
      {
        "sequence": 2,
        "processing_time": 1.5,
        "capable_machines": [
          0,
          1,
          2,
          3,
          4,
          5,
          6,
          7
        ],
        "status": "pending"
      },
      {
        "sequence": 3,
        "processing_time": 1.4,
        "capable_machines": [
          0,
          1,
          2,
          3,
          4,
          5,
          6,
          7
        ],
        "status": "pending"
      }
    ]
  },
  "7876": {
    "transaction_id": 7876,
    "product": "CP08-423",
    "is_important": false,
    "lcd_date": "2024-02-29T00:00:00",
    "total_sequences": 2,
    "tasks": [
      {
        "sequence": 1,
        "processing_time": 1.9,
        "capable_machines": [
          6,
          7,
          8
        ],
        "status": "pending"
      },
      {
        "sequence": 2,
        "processing_time": 1.5,
        "capable_machines": [
          0,
          1,
          2,
          3,
          4,
          5,
          6,
          7
        ],
        "status": "pending"
      }
    ]
  },
  "7875": {
    "transaction_id": 7875,
    "product": "CP08-422",
    "is_important": false,
    "lcd_date": "2024-03-03T00:00:00",
    "total_sequences": 3,
    "tasks": [
      {
        "sequence": 1,
        "processing_time": 1.9,
        "capable_machines": [
          3,
          4,
          5
        ],
        "status": "pending"
      },
      {
        "sequence": 2,
        "processing_time": 1.5,
        "capable_machines": [
          0,
          1,
          2,
          3,
          4,
          5,
          6,
          7
        ],
        "status": "pending"
      },
      {
        "sequence": 3,
        "processing_time": 1.4,
        "capable_machines": [
          0,
          1,
          2,
          3,
          4,
          5,
          6,
          7
        ],
        "status": "pending"
      }
    ]
  },
  "7874": {
    "transaction_id": 7874,
    "product": "CP08-421",
    "is_important": true,
    "lcd_date": "2024-01-16T00:00:00",
    "total_sequences": 3,
    "tasks": [
      {
        "sequence": 1,
        "processing_time": 1.9,
        "capable_machines": [
          0,
          1,
          2
        ],
        "status": "pending"
      },
      {
        "sequence": 2,
        "processing_time": 1.5,
        "capable_machines": [
          0,
          1,
          2,
          3,
          4,
          5,
          6,
          7
        ],
        "status": "pending"
      },
      {
        "sequence": 3,
        "processing_time": 1.4,
        "capable_machines": [
          0,
          1,
          2,
          3,
          4,
          5,
          6,
          7
        ],
        "status": "pending"
      }
    ]
  },
  "7873": {
    "transaction_id": 7873,
    "product": "CP08-420",
    "is_important": false,
    "lcd_date": "2024-02-06T00:00:00",
    "total_sequences": 3,
    "tasks": [
      {
        "sequence": 1,
        "processing_time": 1.9,
        "capable_machines": [
          6,
          7,
          8
        ],
        "status": "pending"
      },
      {
        "sequence": 2,
        "processing_time": 1.5,
        "capable_machines": [
          0,
          1,
          2,
          3,
          4,
          5,
          6,
          7
        ],
        "status": "pending"
      },
      {
        "sequence": 4,
        "processing_time": 1.4,
        "capable_machines": [
          2,
          3,
          4,
          5,
          6,
          7,
          8,
          9
        ],
        "status": "pending"
      }
    ]
  },
  "7872": {
    "transaction_id": 7872,
    "product": "CP08-419",
    "is_important": false,
    "lcd_date": "2024-02-26T00:00:00",
    "total_sequences": 3,
    "tasks": [
      {
        "sequence": 1,
        "processing_time": 1.9,
        "capable_machines": [
          3,
          4,
          5
        ],
        "status": "pending"
      },
      {
        "sequence": 2,
        "processing_time": 1.5,
        "capable_machines": [
          0,
          1,
          2,
          3,
          4,
          5,
          6,
          7
        ],
        "status": "pending"
      },
      {
        "sequence": 3,
        "processing_time": 1.4,
        "capable_machines": [
          0,
          1,
          2,
          3,
          4,
          5,
          6,
          7
        ],
        "status": "pending"
      }
    ]
  },
  "7871": {
    "transaction_id": 7871,
    "product": "CP08-418",
    "is_important": false,
    "lcd_date": "2024-02-11T00:00:00",
    "total_sequences": 3,
    "tasks": [
      {
        "sequence": 1,
        "processing_time": 1.9,
        "capable_machines": [
          0,
          1,
          2
        ],
        "status": "pending"
      },
      {
        "sequence": 2,
        "processing_time": 1.5,
        "capable_machines": [
          0,
          1,
          2,
          3,
          4,
          5,
          6,
          7
        ],
        "status": "pending"
      },
      {
        "sequence": 3,
        "processing_time": 1.4,
        "capable_machines": [
          0,
          1,
          2,
          3,
          4,
          5,
          6,
          7
        ],
        "status": "pending"
      }
    ]
  },
  "7971": {
    "transaction_id": 7971,
    "product": "CM10-013",
    "is_important": true,
    "lcd_date": "2024-01-17T00:00:00",
    "total_sequences": 4,
    "tasks": [
      {
        "sequence": 1,
        "processing_time": 1.9,
        "capable_machines": [
          6,
          7,
          8
        ],
        "status": "pending"
      },
      {
        "sequence": 2,
        "processing_time": 1.5,
        "capable_machines": [
          0,
          1,
          2,
          3,
          4,
          5,
          6,
          7
        ],
        "status": "pending"
      },
      {
        "sequence": 3,
        "processing_time": 1.4,
        "capable_machines": [
          0,
          1,
          2,
          3,
          4,
          5,
          6,
          7
        ],
        "status": "pending"
      },
      {
        "sequence": 4,
        "processing_time": 1.3,
        "capable_machines": [
          2,
          3,
          4,
          5,
          6,
          7,
          8,
          9
        ],
        "status": "pending"
      }
    ]
  },
  "7870": {
    "transaction_id": 7870,
    "product": "CP08-417",
    "is_important": false,
    "lcd_date": "2024-02-27T00:00:00",
    "total_sequences": 3,
    "tasks": [
      {
        "sequence": 2,
        "processing_time": 1.9,
        "capable_machines": [
          0,
          1,
          2,
          3,
          4,
          5,
          6,
          7
        ],
        "status": "pending"
      },
      {
        "sequence": 3,
        "processing_time": 1.2,
        "capable_machines": [
          0,
          1,
          2,
          3,
          4,
          5,
          6,
          7
        ],
        "status": "pending"
      },
      {
        "sequence": 4,
        "processing_time": 1.4,
        "capable_machines": [
          2,
          3,
          4,
          5,
          6,
          7,
          8,
          9
        ],
        "status": "pending"
      }
    ]
  },
  "7869": {
    "transaction_id": 7869,
    "product": "CP08-416",
    "is_important": false,
    "lcd_date": "2024-02-24T00:00:00",
    "total_sequences": 3,
    "tasks": [
      {
        "sequence": 1,
        "processing_time": 1.9,
        "capable_machines": [
          3,
          4,
          5
        ],
        "status": "pending"
      },
      {
        "sequence": 2,
        "processing_time": 1.5,
        "capable_machines": [
          0,
          1,
          2,
          3,
          4,
          5,
          6,
          7
        ],
        "status": "pending"
      },
      {
        "sequence": 3,
        "processing_time": 1.4,
        "capable_machines": [
          0,
          1,
          2,
          3,
          4,
          5,
          6,
          7
        ],
        "status": "pending"
      }
    ]
  },
  "7868": {
    "transaction_id": 7868,
    "product": "CP08-400",
    "is_important": false,
    "lcd_date": "2024-03-04T00:00:00",
    "total_sequences": 2,
    "tasks": [
      {
        "sequence": 1,
        "processing_time": 1.9,
        "capable_machines": [
          0,
          1,
          2
        ],
        "status": "pending"
      },
      {
        "sequence": 2,
        "processing_time": 1.5,
        "capable_machines": [
          0,
          1,
          2,
          3,
          4,
          5,
          6,
          7
        ],
        "status": "pending"
      }
    ]
  },
  "7867": {
    "transaction_id": 7867,
    "product": "CP08-384",
    "is_important": false,
    "lcd_date": "2024-02-20T00:00:00",
    "total_sequences": 3,
    "tasks": [
      {
        "sequence": 1,
        "processing_time": 1.9,
        "capable_machines": [
          6,
          7,
          8
        ],
        "status": "pending"
      },
      {
        "sequence": 2,
        "processing_time": 1.5,
        "capable_machines": [
          0,
          1,
          2,
          3,
          4,
          5,
          6,
          7
        ],
        "status": "pending"
      },
      {
        "sequence": 3,
        "processing_time": 1.4,
        "capable_machines": [
          0,
          1,
          2,
          3,
          4,
          5,
          6,
          7
        ],
        "status": "pending"
      }
    ]
  },
  "7866": {
    "transaction_id": 7866,
    "product": "CP08-368A",
    "is_important": false,
    "lcd_date": "2024-02-18T00:00:00",
    "total_sequences": 4,
    "tasks": [
      {
        "sequence": 1,
        "processing_time": 2.5,
        "capable_machines": [
          0,
          1,
          2
        ],
        "status": "pending"
      },
      {
        "sequence": 2,
        "processing_time": 1.9,
        "capable_machines": [
          0,
          1,
          2,
          3,
          4,
          5,
          6,
          7
        ],
        "status": "pending"
      },
      {
        "sequence": 3,
        "processing_time": 1.8,
        "capable_machines": [
          0,
          1,
          2,
          3,
          4,
          5,
          6,
          7
        ],
        "status": "pending"
      },
      {
        "sequence": 4,
        "processing_time": 1.8,
        "capable_machines": [
          2,
          3,
          4,
          5,
          6,
          7,
          8,
          9
        ],
        "status": "pending"
      }
    ]
  },
  "7865": {
    "transaction_id": 7865,
    "product": "CP08-368",
    "is_important": false,
    "lcd_date": "2024-02-11T00:00:00",
    "total_sequences": 2,
    "tasks": [
      {
        "sequence": 4,
        "processing_time": 1.6,
        "capable_machines": [
          2,
          3,
          4,
          5,
          6,
          7,
          8,
          9
        ],
        "status": "pending"
      },
      {
        "sequence": 5,
        "processing_time": 1.0,
        "capable_machines": [
          2,
          3,
          4,
          5,
          6,
          7,
          8,
          9
        ],
        "status": "pending"
      }
    ]
  },
  "7864": {
    "transaction_id": 7864,
    "product": "CP08-357",
    "is_important": false,
    "lcd_date": "2024-02-16T00:00:00",
    "total_sequences": 4,
    "tasks": [
      {
        "sequence": 1,
        "processing_time": 1.9,
        "capable_machines": [
          6,
          7,
          8
        ],
        "status": "pending"
      },
      {
        "sequence": 2,
        "processing_time": 1.5,
        "capable_machines": [
          0,
          1,
          2,
          3,
          4,
          5,
          6,
          7
        ],
        "status": "pending"
      },
      {
        "sequence": 3,
        "processing_time": 1.4,
        "capable_machines": [
          0,
          1,
          2,
          3,
          4,
          5,
          6,
          7
        ],
        "status": "pending"
      },
      {
        "sequence": 4,
        "processing_time": 1.3,
        "capable_machines": [
          2,
          3,
          4,
          5,
          6,
          7,
          8,
          9
        ],
        "status": "pending"
      }
    ]
  },
  "7863": {
    "transaction_id": 7863,
    "product": "CP08-349",
    "is_important": false,
    "lcd_date": "2024-03-14T00:00:00",
    "total_sequences": 2,
    "tasks": [
      {
        "sequence": 1,
        "processing_time": 1.9,
        "capable_machines": [
          0,
          1,
          2
        ],
        "status": "pending"
      },
      {
        "sequence": 4,
        "processing_time": 1.2,
        "capable_machines": [
          2,
          3,
          4,
          5,
          6,
          7,
          8,
          9
        ],
        "status": "pending"
      }
    ]
  },
  "7862": {
    "transaction_id": 7862,
    "product": "CP08-339",
    "is_important": false,
    "lcd_date": "2024-02-06T00:00:00",
    "total_sequences": 3,
    "tasks": [
      {
        "sequence": 2,
        "processing_time": 1.9,
        "capable_machines": [
          0,
          1,
          2,
          3,
          4,
          5,
          6,
          7
        ],
        "status": "pending"
      },
      {
        "sequence": 3,
        "processing_time": 1.2,
        "capable_machines": [
          0,
          1,
          2,
          3,
          4,
          5,
          6,
          7
        ],
        "status": "pending"
      },
      {
        "sequence": 4,
        "processing_time": 1.4,
        "capable_machines": [
          2,
          3,
          4,
          5,
          6,
          7,
          8,
          9
        ],
        "status": "pending"
      }
    ]
  },
  "7861": {
    "transaction_id": 7861,
    "product": "CP08-324",
    "is_important": false,
    "lcd_date": "2024-02-27T00:00:00",
    "total_sequences": 4,
    "tasks": [
      {
        "sequence": 2,
        "processing_time": 1.9,
        "capable_machines": [
          0,
          1,
          2,
          3,
          4,
          5,
          6,
          7
        ],
        "status": "pending"
      },
      {
        "sequence": 3,
        "processing_time": 1.2,
        "capable_machines": [
          0,
          1,
          2,
          3,
          4,
          5,
          6,
          7
        ],
        "status": "pending"
      },
      {
        "sequence": 4,
        "processing_time": 1.4,
        "capable_machines": [
          2,
          3,
          4,
          5,
          6,
          7,
          8,
          9
        ],
        "status": "pending"
      },
      {
        "sequence": 5,
        "processing_time": 1.1,
        "capable_machines": [
          2,
          3,
          4,
          5,
          6,
          7,
          8,
          9
        ],
        "status": "pending"
      }
    ]
  },
  "7860": {
    "transaction_id": 7860,
    "product": "CP08-298",
    "is_important": false,
    "lcd_date": "2024-02-07T00:00:00",
    "total_sequences": 3,
    "tasks": [
      {
        "sequence": 1,
        "processing_time": 1.9,
        "capable_machines": [
          0,
          1,
          2
        ],
        "status": "pending"
      },
      {
        "sequence": 2,
        "processing_time": 1.5,
        "capable_machines": [
          0,
          1,
          2,
          3,
          4,
          5,
          6,
          7
        ],
        "status": "pending"
      },
      {
        "sequence": 3,
        "processing_time": 1.4,
        "capable_machines": [
          0,
          1,
          2,
          3,
          4,
          5,
          6,
          7
        ],
        "status": "pending"
      }
    ]
  },
  "7859": {
    "transaction_id": 7859,
    "product": "CP08-291",
    "is_important": true,
    "lcd_date": "2024-01-16T00:00:00",
    "total_sequences": 2,
    "tasks": [
      {
        "sequence": 1,
        "processing_time": 1.9,
        "capable_machines": [
          6,
          7,
          8
        ],
        "status": "pending"
      },
      {
        "sequence": 4,
        "processing_time": 1.2,
        "capable_machines": [
          2,
          3,
          4,
          5,
          6,
          7,
          8,
          9
        ],
        "status": "pending"
      }
    ]
  },
  "7858": {
    "transaction_id": 7858,
    "product": "CP08-289",
    "is_important": false,
    "lcd_date": "2024-02-12T00:00:00",
    "total_sequences": 4,
    "tasks": [
      {
        "sequence": 1,
        "processing_time": 1.9,
        "capable_machines": [
          0,
          1,
          2
        ],
        "status": "pending"
      },
      {
        "sequence": 2,
        "processing_time": 1.5,
        "capable_machines": [
          0,
          1,
          2,
          3,
          4,
          5,
          6,
          7
        ],
        "status": "pending"
      },
      {
        "sequence": 3,
        "processing_time": 1.4,
        "capable_machines": [
          0,
          1,
          2,
          3,
          4,
          5,
          6,
          7
        ],
        "status": "pending"
      },
      {
        "sequence": 4,
        "processing_time": 1.3,
        "capable_machines": [
          2,
          3,
          4,
          5,
          6,
          7,
          8,
          9
        ],
        "status": "pending"
      }
    ]
  },
  "7857": {
    "transaction_id": 7857,
    "product": "CP08-259",
    "is_important": false,
    "lcd_date": "2024-01-29T00:00:00",
    "total_sequences": 4,
    "tasks": [
      {
        "sequence": 1,
        "processing_time": 1.9,
        "capable_machines": [
          0,
          1,
          2
        ],
        "status": "pending"
      },
      {
        "sequence": 2,
        "processing_time": 1.5,
        "capable_machines": [
          0,
          1,
          2,
          3,
          4,
          5,
          6,
          7
        ],
        "status": "pending"
      },
      {
        "sequence": 3,
        "processing_time": 1.4,
        "capable_machines": [
          0,
          1,
          2,
          3,
          4,
          5,
          6,
          7
        ],
        "status": "pending"
      },
      {
        "sequence": 5,
        "processing_time": 1.1,
        "capable_machines": [
          2,
          3,
          4,
          5,
          6,
          7,
          8,
          9
        ],
        "status": "pending"
      }
    ]
  },
  "7856": {
    "transaction_id": 7856,
    "product": "CP08-257",
    "is_important": false,
    "lcd_date": "2024-02-11T00:00:00",
    "total_sequences": 3,
    "tasks": [
      {
        "sequence": 1,
        "processing_time": 1.9,
        "capable_machines": [
          3,
          4,
          5
        ],
        "status": "pending"
      },
      {
        "sequence": 2,
        "processing_time": 1.5,
        "capable_machines": [
          0,
          1,
          2,
          3,
          4,
          5,
          6,
          7
        ],
        "status": "pending"
      },
      {
        "sequence": 3,
        "processing_time": 1.4,
        "capable_machines": [
          0,
          1,
          2,
          3,
          4,
          5,
          6,
          7
        ],
        "status": "pending"
      }
    ]
  },
  "7855": {
    "transaction_id": 7855,
    "product": "CP08-256",
    "is_important": false,
    "lcd_date": "2024-02-20T00:00:00",
    "total_sequences": 2,
    "tasks": [
      {
        "sequence": 1,
        "processing_time": 1.9,
        "capable_machines": [
          0,
          1,
          2
        ],
        "status": "pending"
      },
      {
        "sequence": 4,
        "processing_time": 1.2,
        "capable_machines": [
          2,
          3,
          4,
          5,
          6,
          7,
          8,
          9
        ],
        "status": "pending"
      }
    ]
  },
  "7854": {
    "transaction_id": 7854,
    "product": "CP08-231G",
    "is_important": false,
    "lcd_date": "2024-03-08T00:00:00",
    "total_sequences": 2,
    "tasks": [
      {
        "sequence": 1,
        "processing_time": 1.9,
        "capable_machines": [
          3,
          4,
          5
        ],
        "status": "pending"
      },
      {
        "sequence": 2,
        "processing_time": 1.5,
        "capable_machines": [
          0,
          1,
          2,
          3,
          4,
          5,
          6,
          7
        ],
        "status": "pending"
      }
    ]
  },
  "7853": {
    "transaction_id": 7853,
    "product": "CP08-231F",
    "is_important": false,
    "lcd_date": "2024-03-12T00:00:00",
    "total_sequences": 2,
    "tasks": [
      {
        "sequence": 1,
        "processing_time": 1.9,
        "capable_machines": [
          0,
          1,
          2
        ],
        "status": "pending"
      },
      {
        "sequence": 2,
        "processing_time": 1.5,
        "capable_machines": [
          0,
          1,
          2,
          3,
          4,
          5,
          6,
          7
        ],
        "status": "pending"
      }
    ]
  },
  "7852": {
    "transaction_id": 7852,
    "product": "CP08-231E",
    "is_important": false,
    "lcd_date": "2024-02-22T00:00:00",
    "total_sequences": 2,
    "tasks": [
      {
        "sequence": 1,
        "processing_time": 1.9,
        "capable_machines": [
          6,
          7,
          8
        ],
        "status": "pending"
      },
      {
        "sequence": 2,
        "processing_time": 1.5,
        "capable_machines": [
          0,
          1,
          2,
          3,
          4,
          5,
          6,
          7
        ],
        "status": "pending"
      }
    ]
  },
  "7851": {
    "transaction_id": 7851,
    "product": "CP08-231D",
    "is_important": true,
    "lcd_date": "2024-01-17T00:00:00",
    "total_sequences": 2,
    "tasks": [
      {
        "sequence": 1,
        "processing_time": 1.9,
        "capable_machines": [
          3,
          4,
          5
        ],
        "status": "pending"
      },
      {
        "sequence": 2,
        "processing_time": 1.5,
        "capable_machines": [
          0,
          1,
          2,
          3,
          4,
          5,
          6,
          7
        ],
        "status": "pending"
      }
    ]
  },
  "7850": {
    "transaction_id": 7850,
    "product": "CP08-231C",
    "is_important": true,
    "lcd_date": "2024-01-17T00:00:00",
    "total_sequences": 3,
    "tasks": [
      {
        "sequence": 1,
        "processing_time": 1.9,
        "capable_machines": [
          0,
          1,
          2
        ],
        "status": "pending"
      },
      {
        "sequence": 2,
        "processing_time": 1.5,
        "capable_machines": [
          0,
          1,
          2,
          3,
          4,
          5,
          6,
          7
        ],
        "status": "pending"
      },
      {
        "sequence": 3,
        "processing_time": 1.4,
        "capable_machines": [
          0,
          1,
          2,
          3,
          4,
          5,
          6,
          7
        ],
        "status": "pending"
      }
    ]
  },
  "7849": {
    "transaction_id": 7849,
    "product": "CP08-231B",
    "is_important": false,
    "lcd_date": "2024-02-28T00:00:00",
    "total_sequences": 6,
    "tasks": [
      {
        "sequence": 1,
        "processing_time": 2.5,
        "capable_machines": [
          6,
          7,
          8
        ],
        "status": "pending"
      },
      {
        "sequence": 2,
        "processing_time": 1.9,
        "capable_machines": [
          0,
          1,
          2,
          3,
          4,
          5,
          6,
          7
        ],
        "status": "pending"
      },
      {
        "sequence": 3,
        "processing_time": 1.8,
        "capable_machines": [
          0,
          1,
          2,
          3,
          4,
          5,
          6,
          7
        ],
        "status": "pending"
      },
      {
        "sequence": 4,
        "processing_time": 1.8,
        "capable_machines": [
          2,
          3,
          4,
          5,
          6,
          7,
          8,
          9
        ],
        "status": "pending"
      },
      {
        "sequence": 5,
        "processing_time": 1.8,
        "capable_machines": [
          2,
          3,
          4,
          5,
          6,
          7,
          8,
          9
        ],
        "status": "pending"
      },
      {
        "sequence": 6,
        "processing_time": 1.7,
        "capable_machines": [
          2,
          3,
          4,
          5,
          6,
          7,
          8,
          9
        ],
        "status": "pending"
      }
    ]
  },
  "7848": {
    "transaction_id": 7848,
    "product": "CP08-231A",
    "is_important": false,
    "lcd_date": "2024-02-13T00:00:00",
    "total_sequences": 3,
    "tasks": [
      {
        "sequence": 1,
        "processing_time": 2.5,
        "capable_machines": [
          3,
          4,
          5
        ],
        "status": "pending"
      },
      {
        "sequence": 2,
        "processing_time": 1.9,
        "capable_machines": [
          0,
          1,
          2,
          3,
          4,
          5,
          6,
          7
        ],
        "status": "pending"
      },
      {
        "sequence": 3,
        "processing_time": 1.8,
        "capable_machines": [
          0,
          1,
          2,
          3,
          4,
          5,
          6,
          7
        ],
        "status": "pending"
      }
    ]
  },
  "7847": {
    "transaction_id": 7847,
    "product": "CP08-231",
    "is_important": false,
    "lcd_date": "2024-02-06T00:00:00",
    "total_sequences": 6,
    "tasks": [
      {
        "sequence": 13,
        "processing_time": 1.3,
        "capable_machines": [
          2,
          3,
          4,
          5,
          6,
          7,
          8,
          9
        ],
        "status": "pending"
      },
      {
        "sequence": 14,
        "processing_time": 1.0,
        "capable_machines": [
          2,
          3,
          4,
          5,
          6,
          7,
          8,
          9
        ],
        "status": "pending"
      },
      {
        "sequence": 15,
        "processing_time": 1.1,
        "capable_machines": [
          2,
          3,
          4,
          5,
          6,
          7,
          8,
          9
        ],
        "status": "pending"
      },
      {
        "sequence": 16,
        "processing_time": 1.1,
        "capable_machines": [
          2,
          3,
          4,
          5,
          6,
          7,
          8,
          9
        ],
        "status": "pending"
      },
      {
        "sequence": 18,
        "processing_time": 1.3,
        "capable_machines": [
          2,
          3,
          4,
          5,
          6,
          7,
          8,
          9
        ],
        "status": "pending"
      },
      {
        "sequence": 19,
        "processing_time": 1.3,
        "capable_machines": [
          2,
          3,
          4,
          5,
          6,
          7,
          8,
          9
        ],
        "status": "pending"
      }
    ]
  },
  "7846": {
    "transaction_id": 7846,
    "product": "CP08-231",
    "is_important": false,
    "lcd_date": "2024-03-03T00:00:00",
    "total_sequences": 6,
    "tasks": [
      {
        "sequence": 13,
        "processing_time": 1.3,
        "capable_machines": [
          2,
          3,
          4,
          5,
          6,
          7,
          8,
          9
        ],
        "status": "pending"
      },
      {
        "sequence": 14,
        "processing_time": 1.0,
        "capable_machines": [
          2,
          3,
          4,
          5,
          6,
          7,
          8,
          9
        ],
        "status": "pending"
      },
      {
        "sequence": 15,
        "processing_time": 1.1,
        "capable_machines": [
          2,
          3,
          4,
          5,
          6,
          7,
          8,
          9
        ],
        "status": "pending"
      },
      {
        "sequence": 16,
        "processing_time": 1.1,
        "capable_machines": [
          2,
          3,
          4,
          5,
          6,
          7,
          8,
          9
        ],
        "status": "pending"
      },
      {
        "sequence": 18,
        "processing_time": 1.3,
        "capable_machines": [
          2,
          3,
          4,
          5,
          6,
          7,
          8,
          9
        ],
        "status": "pending"
      },
      {
        "sequence": 19,
        "processing_time": 1.3,
        "capable_machines": [
          2,
          3,
          4,
          5,
          6,
          7,
          8,
          9
        ],
        "status": "pending"
      }
    ]
  },
  "7845": {
    "transaction_id": 7845,
    "product": "CP08-230",
    "is_important": false,
    "lcd_date": "2024-03-10T00:00:00",
    "total_sequences": 4,
    "tasks": [
      {
        "sequence": 1,
        "processing_time": 1.9,
        "capable_machines": [
          3,
          4,
          5
        ],
        "status": "pending"
      },
      {
        "sequence": 2,
        "processing_time": 1.5,
        "capable_machines": [
          0,
          1,
          2,
          3,
          4,
          5,
          6,
          7
        ],
        "status": "pending"
      },
      {
        "sequence": 3,
        "processing_time": 1.4,
        "capable_machines": [
          0,
          1,
          2,
          3,
          4,
          5,
          6,
          7
        ],
        "status": "pending"
      },
      {
        "sequence": 4,
        "processing_time": 1.3,
        "capable_machines": [
          2,
          3,
          4,
          5,
          6,
          7,
          8,
          9
        ],
        "status": "pending"
      }
    ]
  },
  "7844": {
    "transaction_id": 7844,
    "product": "CP08-158",
    "is_important": false,
    "lcd_date": "2024-03-15T00:00:00",
    "total_sequences": 2,
    "tasks": [
      {
        "sequence": 1,
        "processing_time": 1.9,
        "capable_machines": [
          3,
          4,
          5
        ],
        "status": "pending"
      },
      {
        "sequence": 2,
        "processing_time": 1.5,
        "capable_machines": [
          0,
          1,
          2,
          3,
          4,
          5,
          6,
          7
        ],
        "status": "pending"
      }
    ]
  },
  "7843": {
    "transaction_id": 7843,
    "product": "CP08-056",
    "is_important": false,
    "lcd_date": "2024-01-30T00:00:00",
    "total_sequences": 2,
    "tasks": [
      {
        "sequence": 1,
        "processing_time": 1.9,
        "capable_machines": [
          3,
          4,
          5
        ],
        "status": "pending"
      },
      {
        "sequence": 2,
        "processing_time": 1.5,
        "capable_machines": [
          0,
          1,
          2,
          3,
          4,
          5,
          6,
          7
        ],
        "status": "pending"
      }
    ]
  },
  "7842": {
    "transaction_id": 7842,
    "product": "CP08-012",
    "is_important": false,
    "lcd_date": "2024-03-05T00:00:00",
    "total_sequences": 3,
    "tasks": [
      {
        "sequence": 1,
        "processing_time": 1.9,
        "capable_machines": [
          6,
          7,
          8
        ],
        "status": "pending"
      },
      {
        "sequence": 2,
        "processing_time": 1.5,
        "capable_machines": [
          0,
          1,
          2,
          3,
          4,
          5,
          6,
          7
        ],
        "status": "pending"
      },
      {
        "sequence": 3,
        "processing_time": 1.4,
        "capable_machines": [
          0,
          1,
          2,
          3,
          4,
          5,
          6,
          7
        ],
        "status": "pending"
      }
    ]
  },
  "7999": {
    "transaction_id": 7999,
    "product": "CH04-002",
    "is_important": false,
    "lcd_date": "2024-02-14T00:00:00",
    "total_sequences": 4,
    "tasks": [
      {
        "sequence": 1,
        "processing_time": 1.9,
        "capable_machines": [
          3,
          4,
          5
        ],
        "status": "pending"
      },
      {
        "sequence": 2,
        "processing_time": 1.5,
        "capable_machines": [
          0,
          1,
          2,
          3,
          4,
          5,
          6,
          7
        ],
        "status": "pending"
      },
      {
        "sequence": 3,
        "processing_time": 1.4,
        "capable_machines": [
          0,
          1,
          2,
          3,
          4,
          5,
          6,
          7
        ],
        "status": "pending"
      },
      {
        "sequence": 4,
        "processing_time": 1.3,
        "capable_machines": [
          2,
          3,
          4,
          5,
          6,
          7,
          8,
          9
        ],
        "status": "pending"
      }
    ]
  },
  "7998": {
    "transaction_id": 7998,
    "product": "CH04-001",
    "is_important": false,
    "lcd_date": "2024-03-11T00:00:00",
    "total_sequences": 4,
    "tasks": [
      {
        "sequence": 1,
        "processing_time": 1.9,
        "capable_machines": [
          0,
          1,
          2
        ],
        "status": "pending"
      },
      {
        "sequence": 2,
        "processing_time": 1.5,
        "capable_machines": [
          0,
          1,
          2,
          3,
          4,
          5,
          6,
          7
        ],
        "status": "pending"
      },
      {
        "sequence": 3,
        "processing_time": 1.4,
        "capable_machines": [
          0,
          1,
          2,
          3,
          4,
          5,
          6,
          7
        ],
        "status": "pending"
      },
      {
        "sequence": 4,
        "processing_time": 1.3,
        "capable_machines": [
          2,
          3,
          4,
          5,
          6,
          7,
          8,
          9
        ],
        "status": "pending"
      }
    ]
  },
  "7883": {
    "transaction_id": 7883,
    "product": "CP08-428B",
    "is_important": false,
    "lcd_date": "2024-03-10T00:00:00",
    "total_sequences": 3,
    "tasks": [
      {
        "sequence": 1,
        "processing_time": 2.5,
        "capable_machines": [
          3,
          4,
          5
        ],
        "status": "pending"
      },
      {
        "sequence": 2,
        "processing_time": 1.9,
        "capable_machines": [
          0,
          1,
          2,
          3,
          4,
          5,
          6,
          7
        ],
        "status": "pending"
      },
      {
        "sequence": 3,
        "processing_time": 1.8,
        "capable_machines": [
          0,
          1,
          2,
          3,
          4,
          5,
          6,
          7
        ],
        "status": "pending"
      }
    ]
  },
  "7884": {
    "transaction_id": 7884,
    "product": "CP08-428C",
    "is_important": true,
    "lcd_date": "2024-01-16T00:00:00",
    "total_sequences": 3,
    "tasks": [
      {
        "sequence": 1,
        "processing_time": 1.9,
        "capable_machines": [
          6,
          7,
          8
        ],
        "status": "pending"
      },
      {
        "sequence": 2,
        "processing_time": 1.5,
        "capable_machines": [
          0,
          1,
          2,
          3,
          4,
          5,
          6,
          7
        ],
        "status": "pending"
      },
      {
        "sequence": 3,
        "processing_time": 1.4,
        "capable_machines": [
          0,
          1,
          2,
          3,
          4,
          5,
          6,
          7
        ],
        "status": "pending"
      }
    ]
  },
  "7885": {
    "transaction_id": 7885,
    "product": "CP08-428D",
    "is_important": false,
    "lcd_date": "2024-02-15T00:00:00",
    "total_sequences": 3,
    "tasks": [
      {
        "sequence": 1,
        "processing_time": 1.9,
        "capable_machines": [
          0,
          1,
          2
        ],
        "status": "pending"
      },
      {
        "sequence": 2,
        "processing_time": 1.5,
        "capable_machines": [
          0,
          1,
          2,
          3,
          4,
          5,
          6,
          7
        ],
        "status": "pending"
      },
      {
        "sequence": 3,
        "processing_time": 1.4,
        "capable_machines": [
          0,
          1,
          2,
          3,
          4,
          5,
          6,
          7
        ],
        "status": "pending"
      }
    ]
  },
  "7886": {
    "transaction_id": 7886,
    "product": "CP08-428E",
    "is_important": false,
    "lcd_date": "2024-03-09T00:00:00",
    "total_sequences": 4,
    "tasks": [
      {
        "sequence": 1,
        "processing_time": 1.9,
        "capable_machines": [
          3,
          4,
          5
        ],
        "status": "pending"
      },
      {
        "sequence": 2,
        "processing_time": 1.5,
        "capable_machines": [
          0,
          1,
          2,
          3,
          4,
          5,
          6,
          7
        ],
        "status": "pending"
      },
      {
        "sequence": 3,
        "processing_time": 1.4,
        "capable_machines": [
          0,
          1,
          2,
          3,
          4,
          5,
          6,
          7
        ],
        "status": "pending"
      },
      {
        "sequence": 4,
        "processing_time": 1.3,
        "capable_machines": [
          2,
          3,
          4,
          5,
          6,
          7,
          8,
          9
        ],
        "status": "pending"
      }
    ]
  },
  "7887": {
    "transaction_id": 7887,
    "product": "CP08-431",
    "is_important": true,
    "lcd_date": "2024-01-17T00:00:00",
    "total_sequences": 6,
    "tasks": [
      {
        "sequence": 1,
        "processing_time": 1.9,
        "capable_machines": [
          3,
          4,
          5
        ],
        "status": "pending"
      },
      {
        "sequence": 2,
        "processing_time": 1.5,
        "capable_machines": [
          0,
          1,
          2,
          3,
          4,
          5,
          6,
          7
        ],
        "status": "pending"
      },
      {
        "sequence": 3,
        "processing_time": 1.4,
        "capable_machines": [
          0,
          1,
          2,
          3,
          4,
          5,
          6,
          7
        ],
        "status": "pending"
      },
      {
        "sequence": 4,
        "processing_time": 1.3,
        "capable_machines": [
          2,
          3,
          4,
          5,
          6,
          7,
          8,
          9
        ],
        "status": "pending"
      },
      {
        "sequence": 5,
        "processing_time": 1.3,
        "capable_machines": [
          2,
          3,
          4,
          5,
          6,
          7,
          8,
          9
        ],
        "status": "pending"
      },
      {
        "sequence": 6,
        "processing_time": 1.3,
        "capable_machines": [
          2,
          3,
          4,
          5,
          6,
          7,
          8,
          9
        ],
        "status": "pending"
      }
    ]
  }
}